cppt/bin/__init__.py
cppt/bin/cppt.py
cppt/commands/__init__.py
cppt/commands/compile/__init__.py
cppt/commands/compile/manager.py
cppt/commands/config/__init__.py
cppt/commands/config/manager.py
cppt/commands/create/__init__.py
cppt/commands/create/manager.py
cppt/commands/fetch/__init__.py
cppt/commands/fetch/manager.py
cppt/commands/fetch/server.py
cppt/commands/run/__init__.py
cppt/commands/run/manager.py
cppt/commands/tc/__init__.py
cppt/commands/tc/add/__init__.py
cppt/commands/tc/add/manager.py
cppt/commands/tc/delete/__init__.py
cppt/commands/tc/delete/manager.py
cppt/commands/tc/edit/__init__.py
cppt/commands/tc/edit/manager.py
cppt/commands/tc/view/__init__.py
cppt/commands/tc/view/manager.py
cppt/commands/test/__init__.py
cppt/commands/test/manager.py
cppt/utils/__init__.py
cppt/utils/config_manager.py
cppt/utils/default_config.yaml
cppt/utils/file_manager.py
cppt/utils/folder_manager.py
cppt-2.0.0.dist-info/LICENSE
cppt-2.0.0.dist-info/METADATA
cppt-2.0.0.dist-info/WHEEL
cppt-2.0.0.dist-info/entry_points.txt
cppt-2.0.0.dist-info/top_level.txt
cppt-2.0.0.dist-info/RECORD
