Metadata-Version: 2.1
Name: cppt
Version: 2.0.0
Summary: Command line tool to automate your competitive programming workflow without cluttering your workspace with testcase data
Home-page: https://github.com/vishalagrawal22/CPPT
Author: Vishal Agrawal
Author-email: vishalagrawalva22@gmail.com
Classifier: Programming Language :: Python :: 3
Classifier: Operating System :: OS Independent
Classifier: License :: OSI Approved :: MIT License
Requires-Python: >=3.6
License-File: LICENSE
Requires-Dist: click
Requires-Dist: pyyaml
